ansys/math/core/__init__.py
ansys/math/core/math.py
ansys_math_core-0.2.4.dist-info/licenses/LICENSE
ansys_math_core-0.2.4.dist-info/WHEEL
ansys_math_core-0.2.4.dist-info/METADATA
ansys_math_core-0.2.4.dist-info/RECORD
