Metadata-Version: 2.4
Name: ansys-math-core
Version: 0.2.4
Summary: A Python wrapper for PyAnsys Math libraries.
Author-email: "ANSYS, Inc." <pyansys.core@ansys.com>
Maintainer-email: "ANSYS, Inc." <pyansys.core@ansys.com>
Requires-Python: >=3.10
Classifier: Development Status :: 4 - Beta
Classifier: Programming Language :: Python :: 3.10
Classifier: Programming Language :: Python :: 3.11
Classifier: Programming Language :: Python :: 3.12
Classifier: Programming Language :: Python :: 3.13
Classifier: License :: OSI Approved :: MIT License
Classifier: Operating System :: OS Independent
License-File: LICENSE
Requires-Dist: ansys-mapdl-core>=0.64.0
Requires-Dist: ansys-tools-path>=0.2.4
Requires-Dist: pyansys-tools-versioning>=0.3.3
Requires-Dist: numpy>=1.14.0
Requires-Dist: scipy>=1.3.0
Requires-Dist: Sphinx==8.1.3 ; extra == "doc"
Requires-Dist: ansys-mapdl-core==0.69.3 ; extra == "doc"
Requires-Dist: ansys-mapdl-reader==0.54.2 ; extra == "doc"
Requires-Dist: ansys-sphinx-theme==1.4.2 ; extra == "doc"
Requires-Dist: jupyter_sphinx==0.5.3 ; extra == "doc"
Requires-Dist: jupyterlab==4.3.6 ; extra == "doc"
Requires-Dist: numpydoc==1.8.0 ; extra == "doc"
Requires-Dist: pypandoc==1.15 ; extra == "doc"
Requires-Dist: pytest-sphinx==0.6.3 ; extra == "doc"
Requires-Dist: pyvista[jupyter, trame]==0.45.2 ; extra == "doc"
Requires-Dist: scipy==1.15.2 ; extra == "doc"
Requires-Dist: sphinx-autobuild==2024.10.3 ; extra == "doc"
Requires-Dist: sphinx-autodoc-typehints==3.0.1 ; extra == "doc"
Requires-Dist: sphinx-copybutton==0.5.2 ; extra == "doc"
Requires-Dist: sphinx-design==0.6.1 ; extra == "doc"
Requires-Dist: sphinx-notfound-page==1.1.0 ; extra == "doc"
Requires-Dist: sphinx-gallery==0.19.0 ; extra == "doc"
Requires-Dist: vtk==9.4.2 ; extra == "doc"
Requires-Dist: ansys-mapdl-core==0.69.3 ; extra == "tests"
Requires-Dist: numpy==2.2.4 ; extra == "tests"
Requires-Dist: scipy==1.15.2 ; extra == "tests"
Requires-Dist: pyansys-tools-report==0.8.2 ; extra == "tests"
Requires-Dist: pytest==8.3.5 ; extra == "tests"
Requires-Dist: pytest-cov==6.1.1 ; extra == "tests"
Requires-Dist: pytest-rerunfailures==15.0 ; extra == "tests"
Requires-Dist: pyvista==0.45.2 ; extra == "tests"
Requires-Dist: vtk==9.4.2 ; extra == "tests"
Project-URL: Documentation, https://math.docs.pyansys.com
Project-URL: Homepage, https://github.com/ansys/pyansys-math/
Project-URL: Source, https://github.com/ansys/pyansys-math
Project-URL: Tracker, https://github.com/ansys/pyansys-math/issues
Provides-Extra: doc
Provides-Extra: tests
